README.md
setup.py
changeable/__init__.py
changeable/anchor.py
changeable/dataloader.py
changeable/dataset.py
changeable/transforms.py
changeable/transfunc.py
changeable.egg-info/PKG-INFO
changeable.egg-info/SOURCES.txt
changeable.egg-info/dependency_links.txt
changeable.egg-info/requires.txt
changeable.egg-info/top_level.txt
changeable/losses/__init__.py
changeable/losses/focal_loss.py
changeable/losses/iou_loss.py
changeable/utils/__init__.py
changeable/utils/boxes.py
changeable/utils/data.py
changeable/utils/dataset.py
changeable/utils/display.py