Metadata-Version: 1.2
Name: changeable
Version: 0.0.2
Summary: Data transforms for object detection.
Home-page: https://github.com/yatengLG/Changeable
Author: yatengLG
Author-email: yatenglg@qq.com
License: MIT Licence
Keywords: pip,changeable
Platform: any
Requires-Python: >=3.6
